<?xml version="1.0" encoding="UTF-8"?>
<fontFamilies>
    <fontFamily name="宋体">
        <normal>jaspers/fonts/simsun.ttf</normal>
        <bold>jaspers/fonts/simsun.ttf</bold>
        <italic>jaspers/fonts/simsun.ttf</italic>
        <boldItalic>jaspers/fonts/simsun.ttf</boldItalic>
        <pdfEncoding>Identity-H</pdfEncoding>
        <pdfEmbedded>false</pdfEmbedded>
        <exportFonts>
            <export key="net.sf.jasperreports.html">'STSong-Light', Arial, Helvetica, sans-serif</export>
            <export key="net.sf.jasperreports.xhtml">'STSong-Light', Arial, Helvetica, sans-serif</export>
        </exportFonts>
    </fontFamily>
</fontFamilies>
